Metadata-Version: 2.1
Name: trollformatter
Version: 1.0.2
Summary: A troll code formatter for C, C++ and Java to make your compsci teacher angry.
Home-page: https://gitlab.com/bbworld1/trollformatter
Author: Vincent Wang
Author-email: vwangsf@gmail.com
License: UNKNOWN
Download-URL: https://gitlab.com/bbworld1/trollformatter/-/archive/v1.0.1/trollformatter-v1.0.1.tar.gz
Keywords: troll code-formatter formatter c c++ java
Platform: UNKNOWN
Classifier: Development Status :: 4 - Beta
Classifier: Intended Audience :: Developers
Classifier: Topic :: Software Development :: Build Tools
Classifier: License :: OSI Approved :: GNU General Public License (GPL)
Classifier: Programming Language :: Python :: 3
License-File: LICENSE
